{
    "category": "Utility Networks",
    "description": "Discover connected features in a utility network using connected, subnetwork, upstream, and downstream traces.",
    "formal_name": "TraceUtilityNetwork",
    "ignore": false,
    "images": [
        "trace-utility-network.png"
    ],
    "keywords": [
        "condition barriers",
        "downstream trace",
        "network analysis",
        "subnetwork trace",
        "trace configuration",
        "traversability",
        "upstream trace",
        "utility network",
        "validate consistency"
    ],
    "relevant_apis": [
        "FractionAlong",
        "UtilityAssetType",
        "UtilityDomainNetwork",
        "UtilityElement",
        "UtilityElementTraceResult",
        "UtilityNetwork",
        "UtilityNetworkDefinition",
        "UtilityNetworkSource",
        "UtilityTerminal",
        "UtilityTier",
        "UtilityTraceConfiguration",
        "UtilityTraceParameters",
        "UtilityTraceResult",
        "UtilityTraceType",
        "UtilityTraversability"
    ],
    "snippets": [
        "/src/main/java/com/esri/arcgisruntime/sample/traceutilitynetwork/MainActivity.kt"
    ],
    "title": "Trace utility network"
}
