{
    "category": "Analysis",
    "description": "Perform a line of sight analysis between two points in real time.",
    "formal_name": "LocationLineOfSight",
    "ignore": false,
    "images": [
        "location-line-of-sight.png"
    ],
    "keywords": [
        "3D",
        "line of sight",
        "visibility",
        "visibility analysis"
    ],
    "language": "java",
    "redirect_from": [
        "/android/latest/sample-code/location-line-of-sight.htm"
    ],
    "relevant_apis": [
        "AnalysisOverlay",
        "LocationLineOfSight",
        "SceneView"
    ],
    "snippets": [
        "src/main/java/com/esri/arcgisruntime/sample/locationlineofsight/MainActivity.java"
    ],
    "title": "Location line of sight"
}
