{
    "category": "Analysis",
    "description": "Show a line of sight between two moving objects.",
    "formal_name": "LineOfSightGeoelement",
    "ignore": false,
    "images": [
        "line-of-sight-geoelement.png"
    ],
    "keywords": [
        "3D",
        "line of sight",
        "visibility",
        "visibility analysis"
    ],
    "redirect_from": [
        "/android/latest/sample-code/line-of-sight-geoelement.htm"
    ],
    "relevant_apis": [
        "AnalysisOverlay",
        "GeoElementLineOfSight",
        "LineOfSight.TargetVisibility"
    ],
    "snippets": [
        "/src/main/java/com/esri/arcgisruntime/sample/lineofsightgeoelement/MainActivity.java"
    ],
    "title": "Line of sight geoelement"
}
