{
    "category": "Layers",
    "description": "Load an ArcGIS vector tiled layer from a URL.",
    "formal_name": "ArcgisVectorTiledLayerUrl",
    "ignore": false,
    "images": [
        "arcgis-vectortiledlayer-url.png"
    ],
    "keywords": [
        "tiles",
        "vector",
        "vector basemap",
        "vector tiled layer",
        "vector tiles"
    ],
    "redirect_from": [
        "/android/latest/sample-code/arcgis-vector-tiled-layer-url.htm"
    ],
    "relevant_apis": [
        "ArcGISVectorTiledLayer",
        "Basemap"
    ],
    "snippets": [
        "/src/main/java/com/esri/arcgisruntime/sample/arcgisvectortiledlayerurl/MainActivity.java"
    ],
    "title": "ArcGIS vector tiled layer URL"
}
